poTranslation/__init__.py
poTranslation/core.py
poTranslation/ms_t.py
poTranslation/openai_t.py
poTranslation-0.0.3a1.dist-info/LICENSE
poTranslation-0.0.3a1.dist-info/METADATA
poTranslation-0.0.3a1.dist-info/WHEEL
poTranslation-0.0.3a1.dist-info/entry_points.txt
poTranslation-0.0.3a1.dist-info/top_level.txt
poTranslation-0.0.3a1.dist-info/RECORD
