Metadata-Version: 2.1
Name: poTranslation
Version: 0.0.3a1
Summary: This is a simple python library/CLI tool to translate .po files using various APIs.
Author-email: Steven Guo <author@example.com>
Project-URL: Homepage, https://github.com/StevenGuo42/poTranslation
Project-URL: Repository, https://github.com/StevenGuo42/poTranslation.git
Project-URL: Issue Tracker, https://github.com/StevenGuo42/poTranslation/issues
Classifier: Development Status :: 3 - Alpha
Classifier: Environment :: Console
Classifier: Intended Audience :: Developers
Classifier: Programming Language :: Python :: 3
Classifier: License :: OSI Approved :: BSD License
Classifier: Operating System :: OS Independent
Classifier: Topic :: Software Development :: Localization
Classifier: Topic :: Text Processing :: Linguistic
Classifier: Topic :: Utilities
Classifier: Topic :: Software Development :: Libraries :: Python Modules
Requires-Python: >=3.7
License-File: LICENSE
Requires-Dist: click
Requires-Dist: requests
Requires-Dist: polib
Requires-Dist: tqdm
Requires-Dist: python-dotenv
Requires-Dist: openai
